{
	"result": [{
			"name": "List Token",
			"link": "https://i.ibb.co/41vKc4x/1548340163416.jpg",
			"linkliff": "line://app/1602687308-GXq4Vvk9?type=text&text=token%20list"
		},
		{
			"name": "Login Sb",
			"link": "https://i.ibb.co/B4mMt6T/1548341661798.jpg",
			"linkliff": "line://app/1602687308-GXq4Vvk9?type=text&text=.login%20sb"
		},
		{
			"name": "Login Pro",
			"link": "https://i.ibb.co/xX2Zzdd/IMG-20181220-204012.jpg",
			"linkliff": "line://app/1602687308-GXq4Vvk9?type=text&text=.pro%20login"
		},
		{
			"name": "All Menu",
			"link": "https://i.ibb.co/B4mMt6T/1548341661798.jpg",
			"linkliff": "line://app/1602687308-GXq4Vvk9?type=text&text=help%20menu"
		},
		{
			"name": "Data User",
			"link": "https://i.ibb.co/41vKc4x/1548340163416.jpg",
			"linkliff": "line://app/1602687308-GXq4Vvk9?type=text&text=.data%20user"
		}
	]
}
